{
    "Cible": "Ennemie",
    "Coût de mana": 1,
    "Coût de rage": 0,
    "Coût de vigueur": 0,
    "Effet": [
        {
            "Cible": "Soi-même",
            "Portée": "Individuel",
            "Stat": "Armure magique",
            "Tours actifs": 3,
            "Type": "Up par valeur",
            "Valeur de l'effet": 0,
            "Value": -2500
        },
        {
            "Cible": "Soi-même",
            "Portée": "Individuel",
            "Stat": "Armure physique",
            "Tours actifs": 3,
            "Type": "Up par valeur",
            "Valeur de l'effet": 0,
            "Value": -4000
        }
    ],
    "Forme": "Standard",
    "Niveau": 1,
    "Nom": "Malédiction de l'anneau",
    "Photo": "default.png",
    "Portée": "Individuel"
}

