{
    "Aggro": [
        {
            "Current": 0,
            "Max": 9999
        }
    ],
    "Armure magique": [
        {
            "Current": 0,
            "Max": 0
        }
    ],
    "Armure physique": [
        {
            "Current": 0,
            "Max": 0
        }
    ],
    "Buf-debuf": [
        {
            "Buf-all-stats": ",,,,,,,",
            "Buf-is-percent": false,
            "Buf-type": 0,
            "Buf-value": 0,
            "buf-passive-enabled": false
        },
        {
            "Buf-all-stats": ",,,,,,,",
            "Buf-is-percent": false,
            "Buf-type": 1,
            "Buf-value": 0,
            "buf-passive-enabled": false
        },
        {
            "Buf-all-stats": ",,,,,,,,,",
            "Buf-is-percent": true,
            "Buf-type": 2,
            "Buf-value": 0,
            "buf-passive-enabled": false
        },
        {
            "Buf-all-stats": ",,,,,,,",
            "Buf-is-percent": false,
            "Buf-type": 3,
            "Buf-value": 0,
            "buf-passive-enabled": false
        },
        {
            "Buf-all-stats": ",,,,,,,",
            "Buf-is-percent": false,
            "Buf-type": 4,
            "Buf-value": 0,
            "buf-passive-enabled": false
        },
        {
            "Buf-all-stats": ",,,,,,,,",
            "Buf-is-percent": true,
            "Buf-type": 5,
            "Buf-value": 0,
            "buf-passive-enabled": false
        },
        {
            "Buf-all-stats": ",,,,,,,",
            "Buf-is-percent": false,
            "Buf-type": 6,
            "Buf-value": 0,
            "buf-passive-enabled": false
        },
        {
            "Buf-all-stats": ",,,,,,,",
            "Buf-is-percent": false,
            "Buf-type": 7,
            "Buf-value": 0,
            "buf-passive-enabled": false
        },
        {
            "Buf-all-stats": ",,,,,,,",
            "Buf-is-percent": true,
            "Buf-type": 8,
            "Buf-value": 0,
            "buf-passive-enabled": false
        },
        {
            "Buf-all-stats": ",,,,,,,",
            "Buf-is-percent": true,
            "Buf-type": 9,
            "Buf-value": 0,
            "buf-passive-enabled": false
        },
        {
            "Buf-all-stats": ",,,,,,,",
            "Buf-is-percent": true,
            "Buf-type": 10,
            "Buf-value": 0,
            "buf-passive-enabled": false
        },
        {
            "Buf-all-stats": ",,,,,,,",
            "Buf-is-percent": true,
            "Buf-type": 11,
            "Buf-value": 0,
            "buf-passive-enabled": false
        }
    ],
    "Classe": "standard",
    "Couleur": "orange",
    "Cout critique": [
        {
            "Current": 12,
            "Max": 12
        }
    ],
    "Esquive": [
        {
            "Current": 6,
            "Max": 6
        }
    ],
    "Exp": 0,
    "Forme": "",
    "Mana": [
        {
            "Current": 70,
            "Max": 70
        }
    ],
    "Niveau": 1,
    "Nom": "Azrak Ombresang",
    "Nom court": "Azrak",
    "PV": [
        {
            "Current": 145,
            "Max": 145
        }
    ],
    "Photo": "",
    "Pouvoir magique": [
        {
            "Current": 10,
            "Max": 10
        }
    ],
    "Pouvoir physique": [
        {
            "Current": 20,
            "Max": 20
        }
    ],
    "Rage": [
        {
            "Current": 0,
            "Max": 0
        }
    ],
    "Rang": 4,
    "Regen vitesse": [
        {
            "Current": 10,
            "Max": 10
        }
    ],
    "Regeneration Mana": [
        {
            "Current": 7,
            "Max": 7
        }
    ],
    "Regeneration PV": [
        {
            "Current": 7,
            "Max": 7
        }
    ],
    "Regeneration vigueur": [
        {
            "Current": 5,
            "Max": 5
        }
    ],
    "Taux aggro": [
        {
            "Current": 1,
            "Max": 1
        }
    ],
    "Taux rage": [
        {
            "Current": 0,
            "Max": 0
        }
    ],
    "Tx-rx": [
        {
            "Tx-rx-size": 0,
            "Tx-rx-type": 0
        },
        {
            "Tx-rx-size": 0,
            "Tx-rx-type": 1
        },
        {
            "Tx-rx-size": 0,
            "Tx-rx-type": 2
        },
        {
            "Tx-rx-size": 0,
            "Tx-rx-type": 3
        },
        {
            "Tx-rx-size": 0,
            "Tx-rx-type": 4
        },
        {
            "Tx-rx-size": 0,
            "Tx-rx-type": 5
        }
    ],
    "Type": "Hero",
    "Vigueur": [
        {
            "Current": 130,
            "Max": 130
        }
    ],
    "Vitesse": [
        {
            "Current": 10,
            "Max": 10
        }
    ],
    "is-blocking-atk": false,
    "is_crit_heal_after_crit": false,
    "is_damage_tx_heal_needy_ally": false,
    "is_first_round": false,
    "is_heal_atk_blocked": false,
    "is_random_target": true,
    "m_MaxNbActionsInRound": 1,
    "nb-actions-in-round": 0
}

